yamello/__init__.py
yamello/core.py
yamello/yamello_token.py
yamello-0.0.2.dist-info/LICENSE
yamello-0.0.2.dist-info/METADATA
yamello-0.0.2.dist-info/WHEEL
yamello-0.0.2.dist-info/top_level.txt
yamello-0.0.2.dist-info/RECORD
