Metadata-Version: 2.1
Name: yamello
Version: 0.0.2
Summary: serialize & de-serialize yamello files (which are a true subset of actual yaml>=1.1)
Home-page: https://gitlab.com/berlinade/yamello
Author: codima
License: GPLv3
Platform: unix
Platform: linux
Classifier: Development Status :: 3 - Alpha
Classifier: License :: OSI Approved :: GNU General Public License v3 (GPLv3)
Classifier: Operating System :: OS Independent
Classifier: Programming Language :: Python :: 3
Classifier: Programming Language :: Python :: 3 :: Only
Classifier: Programming Language :: Python :: 3.11
Requires-Python: >=3.10
License-File: LICENSE
